LICENSE
MANIFEST.in
README.rst
setup.cfg
setup.py
syncer.py
docs/Makefile
docs/conf.py
docs/index.rst
docs/make.bat
syncer.egg-info/PKG-INFO
syncer.egg-info/SOURCES.txt
syncer.egg-info/dependency_links.txt
syncer.egg-info/not-zip-safe
syncer.egg-info/top_level.txt
tests/test_py34.py
tests/test_py35.py