Metadata-Version: 1.1
Name: syncer
Version: 1.3.0
Summary: Async to sync converter
Home-page: https://github.com/miyakogi/syncer
Author: Hiroyuki Takagi
Author-email: miyako.dev@gmail.com
License: MIT
Keywords: syncer
Platform: UNKNOWN
Classifier: Development Status :: 5 - Production/Stable
Classifier: Intended Audience :: Developers
Classifier: License :: OSI Approved :: MIT License
Classifier: Natural Language :: English
Classifier: Programming Language :: Python :: 3
Classifier: Programming Language :: Python :: 3 :: Only
Classifier: Programming Language :: Python :: 3.4
Classifier: Programming Language :: Python :: 3.5
Classifier: Programming Language :: Python :: 3.6
